{
	"variants": {
		"normal": [{
			"model": "sevendaystomine:asphalt_0",
			"weight": 70
		}, {
			"model": "sevendaystomine:asphalt_1",
			"weight": 10
		}, {
			"model": "sevendaystomine:asphalt_1",
			"y": 90,
			"weight": 10
		}, {
			"model": "sevendaystomine:asphalt_1",
			"y": 180,
			"weight": 10
		}, {
			"model": "sevendaystomine:asphalt_1",
			"y": 270,
			"weight": 10
		}, {
			"model": "sevendaystomine:asphalt_2",
			"weight": 10
		}, {
			"model": "sevendaystomine:asphalt_2",
			"y": 90,
			"weight": 10
		}, {
			"model": "sevendaystomine:asphalt_2",
			"y": 180,
			"weight": 10
		}, {
			"model": "sevendaystomine:asphalt_2",
			"y": 270,
			"weight": 10
		}, {
			"model": "sevendaystomine:asphalt_3",
			"weight": 10
		}, {
			"model": "sevendaystomine:asphalt_3",
			"y": 90,
			"weight": 10
		}, {
			"model": "sevendaystomine:asphalt_3",
			"y": 180,
			"weight": 10
		}, {
			"model": "sevendaystomine:asphalt_3",
			"y": 270,
			"weight": 10
		}, {
			"model": "sevendaystomine:asphalt_4",
			"weight": 10
		}, {
			"model": "sevendaystomine:asphalt_4",
			"y": 90,
			"weight": 10
		}, {
			"model": "sevendaystomine:asphalt_4",
			"y": 180,
			"weight": 10
		}, {
			"model": "sevendaystomine:asphalt_4",
			"y": 270,
			"weight": 10
		}, {
			"model": "sevendaystomine:asphalt_5",
			"weight": 10
		}, {
			"model": "sevendaystomine:asphalt_5",
			"y": 90,
			"weight": 10
		}, {
			"model": "sevendaystomine:asphalt_5",
			"y": 180,
			"weight": 10
		}, {
			"model": "sevendaystomine:asphalt_5",
			"y": 270,
			"weight": 10
		}, {
			"model": "sevendaystomine:asphalt_6",
			"y": 0,
			"weight": 1
		}, {
			"model": "sevendaystomine:asphalt_6",
			"y": 90,
			"weight": 1
		}, {
			"model": "sevendaystomine:asphalt_6",
			"y": 180,
			"weight": 1
		}, {
			"model": "sevendaystomine:asphalt_6",
			"y": 270,
			"weight": 1
		}]
	}
}