{
	"credit": "Made with Blockbench",
	"textures": {
		"0": "blocks/bone_block_side",
		"1": "blocks/clay",
		"2": "sevendaystomine:blocks/antibiotics"
	},
	"elements": [
		{
			"from": [5.75, 1, 5.75],
			"to": [10.25, 8, 10.25],
			"faces": {
				"north": {"uv": [0, 7, 4.5, 14], "texture": "#2"},
				"east": {"uv": [4.5, 0, 9, 7], "texture": "#2"},
				"south": {"uv": [0, 0, 4.5, 7], "texture": "#2"},
				"west": {"uv": [4.5, 7, 9, 14], "texture": "#2"},
				"up": {"uv": [11.5, 0, 16, 4.5], "texture": "#2"},
				"down": {"uv": [11.5, 0, 16, 4.5], "texture": "#2"}
			}
		},
		{
			"from": [6.75, 9, 6.75],
			"to": [9.25, 10.5, 9.25],
			"faces": {
				"north": {"uv": [0, 0, 2.5, 1.5], "texture": "#1"},
				"east": {"uv": [0, 0, 2.5, 1.5], "texture": "#1"},
				"south": {"uv": [0, 0, 2.5, 1.5], "texture": "#1"},
				"west": {"uv": [0, 0, 2.5, 1.5], "texture": "#1"},
				"up": {"uv": [0, 0, 2.5, 2.5], "texture": "#1"},
				"down": {"uv": [0, 0, 2.5, 2.5], "texture": "#1"}
			}
		},
		{
			"from": [6, 8, 6],
			"to": [10, 9, 10],
			"faces": {
				"north": {"uv": [0, 0, 4, 1], "texture": "#0"},
				"east": {"uv": [0, 0, 4, 1], "texture": "#0"},
				"south": {"uv": [0, 0, 4, 1], "texture": "#0"},
				"west": {"uv": [0, 0, 4, 1], "texture": "#0"},
				"up": {"uv": [0, 0, 4, 4], "texture": "#0"},
				"down": {"uv": [0, 0, 4, 4], "texture": "#0"}
			}
		},
		{
			"from": [6, 0, 6],
			"to": [10, 1, 10],
			"faces": {
				"north": {"uv": [0, 0, 4, 1], "texture": "#0"},
				"east": {"uv": [0, 0, 4, 1], "texture": "#0"},
				"south": {"uv": [0, 0, 4, 1], "texture": "#0"},
				"west": {"uv": [0, 0, 4, 1], "texture": "#0"},
				"up": {"uv": [0, 0, 4, 4], "texture": "#0"},
				"down": {"uv": [0, 0, 4, 4], "texture": "#0"}
			}
		}
	],
	"display": {
		"thirdperson_righthand": {
			"scale": [0.7, 0.7, 0.7],
			"translation": [0, 0, 0],
			"rotation": [0, 90, 0]
		},
		"thirdperson_lefthand": {
			"scale": [0.7, 0.7, 0.7],
			"rotation": [0, -90, 0]
		},
		"firstperson_righthand": {
			"scale": [0.7, 0.7, 0.7],
			"translation": [1.5, 5.5, 0],
			"rotation": [-16, -60, 0]
		},
		"firstperson_lefthand": {
			"scale": [0.7, 0.7, 0.7],
			"rotation": [-16, -60, 0],
			"translation": [1.5, 5.5, 0]
		},
		"head": {
			"translation": [0, -4, -7.5],
			"rotation": [47, 0, 0]
		},
		"ground": {
			"scale": [0.7, 0.7, 0.7],
			"translation": [0, 1.5, 0]
		},
		"fixed": {
			"scale": [1.3, 1.3, 1.3],
			"rotation": [0, 180, 0],
			"translation": [0, 3.5, 0]
		},
		"gui": {
			"scale": [1.3, 1.3, 1.3],
			"rotation": [30, -45, 0],
			"translation": [0, 3.25, 0]
		}
	}
}